lowrankdensity/.DS_Store
lowrankdensity/__init__.py
lowrankdensity/datasets/__init__.py
lowrankdensity/datasets/_generate_samples.py
lowrankdensity/models/.DS_Store
lowrankdensity/models/__init__.py
lowrankdensity/models/continuous.py
lowrankdensity/models/discrete.py
lowrankdensity/viz/_2Dhistogram.py
lowrankdensity/viz/_3Dsurfacedensity.py
lowrankdensity/viz/__init__.py
Lowrankdensity-0.1.0.dist-info/LICENSE
Lowrankdensity-0.1.0.dist-info/METADATA
Lowrankdensity-0.1.0.dist-info/WHEEL
Lowrankdensity-0.1.0.dist-info/top_level.txt
Lowrankdensity-0.1.0.dist-info/RECORD
