Metadata-Version: 2.1
Name: Lowrankdensity
Version: 0.1.0
Summary: Python package for Low rank density estimation.
Home-page: https://github.com/hi-paris/Lowrankdensity
Author: Julien Chhor, Olga Klopp, Alexandre Tsybakov supported by Laurène David, Shreshtha Shaurya and Gaëtan Brison Hi! PARIS Engineering Team
Author-email: engineer.hi.paris@gmail.com
License: MIT license
Keywords: Lowrankdensity
Platform: UNKNOWN
Classifier: Development Status :: 2 - Pre-Alpha
Classifier: Intended Audience :: Developers
Classifier: License :: OSI Approved :: MIT License
Classifier: Environment :: Console
Classifier: Operating System :: OS Independent
Classifier: Operating System :: POSIX :: Linux
Classifier: Operating System :: MacOS
Classifier: Operating System :: POSIX
Classifier: Operating System :: Microsoft :: Windows
Classifier: Natural Language :: English
Classifier: Programming Language :: Python :: 3
Classifier: Programming Language :: Python :: 3.8
Classifier: Programming Language :: Python :: 3.9
Classifier: Programming Language :: Python :: 3.10
Requires-Python: >=3.8
License-File: LICENSE
Requires-Dist: numpy
Requires-Dist: scipy
Requires-Dist: pandas
Requires-Dist: matplotlib
Requires-Dist: plotly
